swiftlog/__init__.py
swiftlog/Logger.py
swiftlog-1.2.0.dist-info/licenses/LICENSE
swiftlog-1.2.0.dist-info/METADATA
swiftlog-1.2.0.dist-info/WHEEL
swiftlog-1.2.0.dist-info/RECORD
