Metadata-Version: 2.4
Name: SwiftLog
Version: 1.2.0
Summary: Lightweight, modular logger that can write to console and file.
License: MIT
License-File: LICENSE
Keywords: log,logging,logger
Author: Adem
Author-email: ademocel83@gmail.com
Requires-Python: >=3.9,<4.0
Classifier: License :: OSI Approved :: MIT License
Classifier: Programming Language :: Python :: 3
Classifier: Programming Language :: Python :: 3.9
Classifier: Programming Language :: Python :: 3.10
Classifier: Programming Language :: Python :: 3.11
Classifier: Programming Language :: Python :: 3.12
Classifier: Programming Language :: Python :: 3.13
Classifier: Programming Language :: Python :: 3.14
Project-URL: Homepage, https://github.com/adem-ocel/SwiftLog
Project-URL: Repository, https://github.com/adem-ocel/SwiftLog
